{
    "id":"jackbox-music",
    "name":"Jackbox Music Server",
    "description":"Enjoy Jackbox with remixed audio from the SiIvaGunner group!",
    "image":"https://raw.githubusercontent.com/DerErizzle/JackboxUtility-Music-Server/main/assets/news_images/logo.png",

    "urls":[
        {
            "versions":["1.0.0"],
            "api":"https://raw.githubusercontent.com/DerErizzle/JackboxUtility-Music-Server/main/api/v2/",
            "assets":"https://raw.githubusercontent.com/DerErizzle/JackboxUtility-Music-Server/main/assets"
        }
    ],
    "controller":"jackbox.tv",
    "languages":["en"],
    "links": [
        {
            "icon":"youtube",
            "url":"https://www.youtube.com/@SiIvaGunner",
            "text":"YouTube"
        }
     ]
}